xpense/__init__.py
xpense/cli.py
xpense/config.py
xpense/constants.py
xpense/display.py
xpense/main.py
xpense/storage.py
xpense/utils.py
xpense/dashboard/__init__.py
xpense/dashboard/app.py
xpense/dashboard/charts.py
xpense/dashboard/data.py
xpense/dashboard/filters.py
xpense/dashboard/metrics.py
xpense/dashboard/theme.py
xpense-0.6.0.dist-info/licenses/LICENSE
xpense-0.6.0.dist-info/METADATA
xpense-0.6.0.dist-info/WHEEL
xpense-0.6.0.dist-info/entry_points.txt
xpense-0.6.0.dist-info/top_level.txt
xpense-0.6.0.dist-info/RECORD
