Metadata-Version: 2.4
Name: xpense
Version: 0.6.0
Summary: A beautiful CLI expense and income tracker
Author-email: Gabriel Rockson <gabrielrockson@gmail.com>
License: MIT
Project-URL: Homepage, https://github.com/Gabriel-Rockson/xpense
Project-URL: Repository, https://github.com/Gabriel-Rockson/xpense
Project-URL: Issues, https://github.com/Gabriel-Rockson/xpense/issues
Project-URL: Changelog, https://github.com/Gabriel-Rockson/xpense/blob/main/CHANGELOG.md
Keywords: expense,income,tracker,cli,finance,budget,money,personal-finance
Classifier: Development Status :: 4 - Beta
Classifier: Intended Audience :: End Users/Desktop
Classifier: Topic :: Office/Business :: Financial
Classifier: Topic :: Office/Business :: Financial :: Accounting
Classifier: License :: OSI Approved :: MIT License
Classifier: Programming Language :: Python :: 3
Classifier: Programming Language :: Python :: 3.11
Classifier: Programming Language :: Python :: 3.12
Classifier: Programming Language :: Python :: 3.13
Classifier: Operating System :: OS Independent
Classifier: Environment :: Console
Requires-Python: >=3.11
License-File: LICENSE
Requires-Dist: typer>=0.19.2
Requires-Dist: rich>=13.9.0
Requires-Dist: pydantic-settings>=2.8.1
Requires-Dist: python-dotenv>=1.0.0
Requires-Dist: streamlit>=1.50.0
Requires-Dist: pandas>=2.3.3
Requires-Dist: plotly>=6.3.1
Dynamic: license-file
